test/__init__.py
test/test_dat_file_save.py
test/test_data_extractor.py
test/test_new_tide.py
test/test_utils.py
uhslc_station_tools/__init__.py
uhslc_station_tools/extractor.py
uhslc_station_tools/filter_weights.py
uhslc_station_tools/filtering.py
uhslc_station_tools/sensor.py
uhslc_station_tools/utils.py
uhslc_station_tools-0.0.196.dist-info/LICENSE
uhslc_station_tools-0.0.196.dist-info/METADATA
uhslc_station_tools-0.0.196.dist-info/WHEEL
uhslc_station_tools-0.0.196.dist-info/top_level.txt
uhslc_station_tools-0.0.196.dist-info/RECORD
